basicdata/__init__.py
basicdata/setup.py
basicdata-2.0.0.dist-info/METADATA
basicdata-2.0.0.dist-info/WHEEL
basicdata-2.0.0.dist-info/entry_points.txt
basicdata-2.0.0.dist-info/top_level.txt
basicdata-2.0.0.dist-info/RECORD
