Metadata-Version: 2.1
Name: basicdata
Version: 2.0.0
Summary: basic data for both Chinese and English  中英文的一些基本数据
Home-page: https://github.com/theCoder-WM
Author: William Ma
Author-email: 3327821469@qq.com
License: UNKNOWN
Platform: UNKNOWN
